{
  "stock_data": {
    "ts_code": "600519.SH",
    "fetch_time": "2025-10-28T15:40:01.472798",
    "basic_info": {
      "ts_code": "600519.SH",
      "name": "贵州茅台",
      "area": "贵州",
      "industry": "白酒",
      "market": "主板",
      "list_date": "20010827"
    },
    "daily_data": [
      {
        "ts_code": "600519.SH",
        "trade_date": "20250829",
        "open": 1453.0,
        "high": 1482.58,
        "low": 1452.0,
        "close": 1480.0,
        "pre_close": 1446.1,
        "change": 33.9,
        "pct_chg": 2.3442,
        "vol": 62256.48,
        "amount": 9159701.454
      },
      {
        "ts_code": "600519.SH",
        "trade_date": "20250901",
        "open": 1482.2,
        "high": 1488.0,
        "low": 1465.7,
        "close": 1476.1,
        "pre_close": 1480.0,
        "change": -3.9,
        "pct_chg": -0.2635,
        "vol": 45123.38,
        "amount": 6658918.555
      },
      {
        "ts_code": "600519.SH",
        "trade_date": "20250902",
        "open": 1478.66,
        "high": 1509.0,
        "low": 1478.0,
        "close": 1491.3,
        "pre_close": 1476.1,
        "change": 15.2,
        "pct_chg": 1.0297,
        "vol": 56688.37,
        "amount": 8470012.816
      },
      {
        "ts_code": "600519.SH",
        "trade_date": "20250903",
        "open": 1491.0,
        "high": 1503.5,
        "low": 1466.0,
        "close": 1480.55,
        "pre_close": 1491.3,
        "change": -10.75,
        "pct_chg": -0.7208,
        "vol": 45045.03,
        "amount": 6656011.145
      },
      {
        "ts_code": "600519.SH",
        "trade_date": "20250904",
        "open": 1472.0,
        "high": 1479.3,
        "low": 1460.47,
        "close": 1472.66,
        "pre_close": 1480.55,
        "change": -7.89,
        "pct_chg": -0.5329,
        "vol": 47746.76,
        "amount": 7017084.75
      },
      {
        "ts_code": "600519.SH",
        "trade_date": "20250905",
        "open": 1471.0,
        "high": 1486.97,
        "low": 1464.0,
        "close": 1483.0,
        "pre_close": 1472.66,
        "change": 10.34,
        "pct_chg": 0.7021,
        "vol": 37388.48,
        "amount": 5519312.163
      },
      {
        "ts_code": "600519.SH",
        "trade_date": "20250908",
        "open": 1483.0,
        "high": 1506.44,
        "low": 1477.5,
        "close": 1501.23,
        "pre_close": 1483.0,
        "change": 18.23,
        "pct_chg": 1.2293,
        "vol": 51382.98,
        "amount": 7682065.696
      },
      {
        "ts_code": "600519.SH",
        "trade_date": "20250909",
        "open": 1505.0,
        "high": 1509.95,
        "low": 1493.42,
        "close": 1505.0,
        "pre_close": 1501.23,
        "change": 3.77,
        "pct_chg": 0.2511,
        "vol": 35742.77,
        "amount": 5366650.005
      },
      {
        "ts_code": "600519.SH",
        "trade_date": "20250910",
        "open": 1506.66,
        "high": 1529.95,
        "low": 1496.0,
        "close": 1522.01,
        "pre_close": 1505.0,
        "change": 17.01,
        "pct_chg": 1.1302,
        "vol": 49663.31,
        "amount": 7541460.049
      },
      {
        "ts_code": "600519.SH",
        "trade_date": "20250911",
        "open": 1522.01,
        "high": 1526.02,
        "low": 1508.5,
        "close": 1523.5,
        "pre_close": 1522.01,
        "change": 1.49,
        "pct_chg": 0.0979,
        "vol": 37238.96,
        "amount": 5642778.456
      },
      {
        "ts_code": "600519.SH",
        "trade_date": "20250912",
        "open": 1526.0,
        "high": 1538.02,
        "low": 1510.53,
        "close": 1516.0,
        "pre_close": 1523.5,
        "change": -7.5,
        "pct_chg": -0.4923,
        "vol": 33722.09,
        "amount": 5132184.935
      },
      {
        "ts_code": "600519.SH",
        "trade_date": "20250915",
        "open": 1515.87,
        "high": 1517.48,
        "low": 1501.5,
        "close": 1515.1,
        "pre_close": 1516.0,
        "change": -0.9,
        "pct_chg": -0.0594,
        "vol": 25827.03,
        "amount": 3901929.718
      },
      {
        "ts_code": "600519.SH",
        "trade_date": "20250916",
        "open": 1515.1,
        "high": 1520.99,
        "low": 1496.21,
        "close": 1499.98,
        "pre_close": 1515.1,
        "change": -15.12,
        "pct_chg": -0.998,
        "vol": 32717.89,
        "amount": 4928374.478
      },
      {
        "ts_code": "600519.SH",
        "trade_date": "20250917",
        "open": 1499.99,
        "high": 1510.28,
        "low": 1490.01,
        "close": 1493.0,
        "pre_close": 1499.98,
        "change": -6.98,
        "pct_chg": -0.4653,
        "vol": 30330.54,
        "amount": 4534770.634
      },
      {
        "ts_code": "600519.SH",
        "trade_date": "20250918",
        "open": 1492.0,
        "high": 1497.8,
        "low": 1463.5,
        "close": 1467.96,
        "pre_close": 1493.0,
        "change": -25.04,
        "pct_chg": -1.6772,
        "vol": 49721.25,
        "amount": 7347477.479
      },
      {
        "ts_code": "600519.SH",
        "trade_date": "20250919",
        "open": 1467.99,
        "high": 1475.5,
        "low": 1457.01,
        "close": 1467.97,
        "pre_close": 1467.96,
        "change": 0.01,
        "pct_chg": 0.0007,
        "vol": 32636.62,
        "amount": 4784528.851
      },
      {
        "ts_code": "600519.SH",
        "trade_date": "20250922",
        "open": 1465.09,
        "high": 1467.97,
        "low": 1450.01,
        "close": 1453.35,
        "pre_close": 1467.97,
        "change": -14.62,
        "pct_chg": -0.9959,
        "vol": 34947.08,
        "amount": 5085057.536
      },
      {
        "ts_code": "600519.SH",
        "trade_date": "20250923",
        "open": 1450.5,
        "high": 1457.5,
        "low": 1440.0,
        "close": 1447.42,
        "pre_close": 1453.35,
        "change": -5.93,
        "pct_chg": -0.408,
        "vol": 38663.0,
        "amount": 5588384.388
      },
      {
        "ts_code": "600519.SH",
        "trade_date": "20250924",
        "open": 1434.07,
        "high": 1456.78,
        "low": 1434.07,
        "close": 1442.0,
        "pre_close": 1447.42,
        "change": -5.42,
        "pct_chg": -0.3745,
        "vol": 30743.5,
        "amount": 4443052.872
      },
      {
        "ts_code": "600519.SH",
        "trade_date": "20250925",
        "open": 1442.83,
        "high": 1445.21,
        "low": 1436.0,
        "close": 1439.0,
        "pre_close": 1442.0,
        "change": -3.0,
        "pct_chg": -0.208,
        "vol": 33869.73,
        "amount": 4873274.661
      },
      {
        "ts_code": "600519.SH",
        "trade_date": "20250926",
        "open": 1441.18,
        "high": 1447.11,
        "low": 1428.01,
        "close": 1435.0,
        "pre_close": 1439.0,
        "change": -4.0,
        "pct_chg": -0.278,
        "vol": 45120.71,
        "amount": 6480889.597
      },
      {
        "ts_code": "600519.SH",
        "trade_date": "20250929",
        "open": 1439.38,
        "high": 1469.99,
        "low": 1435.0,
        "close": 1460.86,
        "pre_close": 1435.0,
        "change": 25.86,
        "pct_chg": 1.8021,
        "vol": 53684.03,
        "amount": 7798434.586
      },
      {
        "ts_code": "600519.SH",
        "trade_date": "20250930",
        "open": 1460.0,
        "high": 1460.76,
        "low": 1440.0,
        "close": 1443.99,
        "pre_close": 1460.86,
        "change": -16.87,
        "pct_chg": -1.1548,
        "vol": 39363.62,
        "amount": 5687474.876
      },
      {
        "ts_code": "600519.SH",
        "trade_date": "20251009",
        "open": 1436.0,
        "high": 1439.38,
        "low": 1420.0,
        "close": 1436.78,
        "pre_close": 1443.99,
        "change": -7.21,
        "pct_chg": -0.4993,
        "vol": 54918.12,
        "amount": 7845448.947
      },
      {
        "ts_code": "600519.SH",
        "trade_date": "20251010",
        "open": 1437.6,
        "high": 1439.94,
        "low": 1427.5,
        "close": 1430.0,
        "pre_close": 1436.78,
        "change": -6.78,
        "pct_chg": -0.4719,
        "vol": 36001.44,
        "amount": 5157459.262
      },
      {
        "ts_code": "600519.SH",
        "trade_date": "20251013",
        "open": 1415.7,
        "high": 1422.85,
        "low": 1415.12,
        "close": 1419.2,
        "pre_close": 1430.0,
        "change": -10.8,
        "pct_chg": -0.7552,
        "vol": 46068.8,
        "amount": 6533147.458
      },
      {
        "ts_code": "600519.SH",
        "trade_date": "20251014",
        "open": 1429.99,
        "high": 1464.0,
        "low": 1429.99,
        "close": 1451.02,
        "pre_close": 1419.2,
        "change": 31.82,
        "pct_chg": 2.2421,
        "vol": 66672.33,
        "amount": 9639484.605
      },
      {
        "ts_code": "600519.SH",
        "trade_date": "20251015",
        "open": 1450.98,
        "high": 1463.0,
        "low": 1445.08,
        "close": 1462.0,
        "pre_close": 1451.02,
        "change": 10.98,
        "pct_chg": 0.7567,
        "vol": 42785.4,
        "amount": 6233407.482
      },
      {
        "ts_code": "600519.SH",
        "trade_date": "20251016",
        "open": 1461.92,
        "high": 1484.95,
        "low": 1458.88,
        "close": 1484.91,
        "pre_close": 1462.0,
        "change": 22.91,
        "pct_chg": 1.567,
        "vol": 45730.15,
        "amount": 6749162.949
      },
      {
        "ts_code": "600519.SH",
        "trade_date": "20251017",
        "open": 1483.1,
        "high": 1488.0,
        "low": 1454.03,
        "close": 1455.0,
        "pre_close": 1484.91,
        "change": -29.91,
        "pct_chg": -2.0143,
        "vol": 38085.89,
        "amount": 5594724.9
      },
      {
        "ts_code": "600519.SH",
        "trade_date": "20251020",
        "open": 1455.0,
        "high": 1469.5,
        "low": 1454.88,
        "close": 1457.93,
        "pre_close": 1455.0,
        "change": 2.93,
        "pct_chg": 0.2014,
        "vol": 25949.88,
        "amount": 3793283.759
      },
      {
        "ts_code": "600519.SH",
        "trade_date": "20251021",
        "open": 1459.0,
        "high": 1469.94,
        "low": 1455.5,
        "close": 1462.26,
        "pre_close": 1457.93,
        "change": 4.33,
        "pct_chg": 0.297,
        "vol": 25442.67,
        "amount": 3727984.13
      },
      {
        "ts_code": "600519.SH",
        "trade_date": "20251022",
        "open": 1462.08,
        "high": 1465.73,
        "low": 1456.0,
        "close": 1458.7,
        "pre_close": 1462.26,
        "change": -3.56,
        "pct_chg": -0.2435,
        "vol": 18194.92,
        "amount": 2657486.636
      },
      {
        "ts_code": "600519.SH",
        "trade_date": "20251023",
        "open": 1455.0,
        "high": 1468.8,
        "low": 1447.2,
        "close": 1467.98,
        "pre_close": 1458.7,
        "change": 9.28,
        "pct_chg": 0.6362,
        "vol": 29322.35,
        "amount": 4274652.09
      },
      {
        "ts_code": "600519.SH",
        "trade_date": "20251024",
        "open": 1467.95,
        "high": 1478.88,
        "low": 1449.34,
        "close": 1450.0,
        "pre_close": 1467.98,
        "change": -17.98,
        "pct_chg": -1.2248,
        "vol": 38225.83,
        "amount": 5578603.148
      },
      {
        "ts_code": "600519.SH",
        "trade_date": "20251027",
        "open": 1440.0,
        "high": 1452.49,
        "low": 1435.99,
        "close": 1440.41,
        "pre_close": 1450.0,
        "change": -9.59,
        "pct_chg": -0.6614,
        "vol": 37102.39,
        "amount": 5352667.152
      },
      {
        "ts_code": "600519.SH",
        "trade_date": "20251028",
        "open": 1442.0,
        "high": 1451.2,
        "low": 1441.1,
        "close": 1445.0,
        "pre_close": 1440.41,
        "change": 4.59,
        "pct_chg": 0.3187,
        "vol": 27124.33,
        "amount": 3923817.14
      }
    ],
    "financial_data": {
      "income": {
        "ts_code": "600519.SH",
        "end_date": "20250630",
        "total_revenue": 91093762553.97,
        "revenue": 89389354416.84,
        "operate_profit": 62768973374.37,
        "total_profit": 62778000766.82,
        "n_income": 46986681449.24
      },
      "balance": {
        "ts_code": "600519.SH",
        "end_date": "20250630",
        "total_assets": 292257789095.51,
        "total_liab": 43122202832.76,
        "total_hldr_eqy_exc_min_int": 238646536390.48
      },
      "cashflow": {
        "ts_code": "600519.SH",
        "end_date": "20250630",
        "n_cashflow_act": 13119061031.33,
        "n_cashflow_inv_act": -314350963.69,
        "n_cash_flows_fnc_act": -39892813631.78
      }
    },
    "financial_indicators": [
      {
        "ts_code": "600519.SH",
        "end_date": "20250630",
        "eps": 36.18,
        "roe": 19.2486,
        "roa": 21.0719,
        "debt_to_assets": 14.7549,
        "current_ratio": 5.7297,
        "quick_ratio": 4.4466
      },
      {
        "ts_code": "600519.SH",
        "end_date": "20250331",
        "eps": 21.38,
        "roe": 10.9255,
        "roa": 12.0224,
        "debt_to_assets": 14.143,
        "current_ratio": 6.0749,
        "quick_ratio": 4.8258
      },
      {
        "ts_code": "600519.SH",
        "end_date": "20250331",
        "eps": 21.38,
        "roe": 10.9255,
        "roa": 12.0224,
        "debt_to_assets": 14.143,
        "current_ratio": 6.0749,
        "quick_ratio": 4.8258
      },
      {
        "ts_code": "600519.SH",
        "end_date": "20241231",
        "eps": 68.64,
        "roe": 38.4283,
        "roa": 41.346,
        "debt_to_assets": 19.0448,
        "current_ratio": 4.4541,
        "quick_ratio": 3.4925
      },
      {
        "ts_code": "600519.SH",
        "end_date": "20240930",
        "eps": 48.42,
        "roe": 26.833,
        "roa": 29.63,
        "debt_to_assets": 13.6285,
        "current_ratio": 6.1569,
        "quick_ratio": 4.9116
      },
      {
        "ts_code": "600519.SH",
        "end_date": "20240930",
        "eps": 48.42,
        "roe": 26.833,
        "roa": 29.63,
        "debt_to_assets": 13.6285,
        "current_ratio": 6.1569,
        "quick_ratio": 4.9116
      },
      {
        "ts_code": "600519.SH",
        "end_date": "20240630",
        "eps": 33.19,
        "roe": 19.2038,
        "roa": 20.5428,
        "debt_to_assets": 18.3242,
        "current_ratio": 4.5714,
        "quick_ratio": 3.6312
      },
      {
        "ts_code": "600519.SH",
        "end_date": "20240331",
        "eps": 19.16,
        "roe": 10.5688,
        "roa": 11.707,
        "debt_to_assets": 12.9543,
        "current_ratio": 6.481,
        "quick_ratio": 5.2018
      },
      {
        "ts_code": "600519.SH",
        "end_date": "20231231",
        "eps": 59.49,
        "roe": 36.1755,
        "roa": 38.6036,
        "debt_to_assets": 17.9843,
        "current_ratio": 4.6239,
        "quick_ratio": 3.6704
      },
      {
        "ts_code": "600519.SH",
        "end_date": "20230930",
        "eps": 42.09,
        "roe": 25.4632,
        "roa": 27.8049,
        "debt_to_assets": 14.14,
        "current_ratio": 5.9588,
        "quick_ratio": 4.8408
      },
      {
        "ts_code": "600519.SH",
        "end_date": "20230630",
        "eps": 28.64,
        "roe": 18.0614,
        "roa": 19.7522,
        "debt_to_assets": 13.3925,
        "current_ratio": 6.3536,
        "quick_ratio": 5.0747
      },
      {
        "ts_code": "600519.SH",
        "end_date": "20230630",
        "eps": 28.64,
        "roe": 18.0614,
        "roa": 19.7522,
        "debt_to_assets": 13.3925,
        "current_ratio": 6.3536,
        "quick_ratio": 5.0747
      },
      {
        "ts_code": "600519.SH",
        "end_date": "20230331",
        "eps": 16.55,
        "roe": 10.0028,
        "roa": 11.0282,
        "debt_to_assets": 12.3562,
        "current_ratio": 6.9427,
        "quick_ratio": 5.6683
      },
      {
        "ts_code": "600519.SH",
        "end_date": "20230331",
        "eps": 16.55,
        "roe": 10.0028,
        "roa": 11.0282,
        "debt_to_assets": 12.3562,
        "current_ratio": 6.9427,
        "quick_ratio": 5.6683
      },
      {
        "ts_code": "600519.SH",
        "end_date": "20221231",
        "eps": 49.93,
        "roe": 32.4077,
        "roa": 33.8499,
        "debt_to_assets": 19.421,
        "current_ratio": 4.4147,
        "quick_ratio": 3.6235
      },
      {
        "ts_code": "600519.SH",
        "end_date": "20221231",
        "eps": 49.93,
        "roe": 32.4077,
        "roa": 33.8499,
        "debt_to_assets": 19.421,
        "current_ratio": 4.4147,
        "quick_ratio": 3.6235
      },
      {
        "ts_code": "600519.SH",
        "end_date": "20220930",
        "eps": 35.34,
        "roe": 22.4101,
        "roa": 24.2025,
        "debt_to_assets": 13.8484,
        "current_ratio": 6.1942,
        "quick_ratio": 5.1594
      },
      {
        "ts_code": "600519.SH",
        "end_date": "20220930",
        "eps": 35.34,
        "roe": 22.4101,
        "roa": 24.2025,
        "debt_to_assets": 13.8484,
        "current_ratio": 6.1942,
        "quick_ratio": 5.1594
      },
      {
        "ts_code": "600519.SH",
        "end_date": "20220630",
        "eps": 23.72,
        "roe": 15.6135,
        "roa": 16.5526,
        "debt_to_assets": 17.2578,
        "current_ratio": 4.948,
        "quick_ratio": 4.0993
      },
      {
        "ts_code": "600519.SH",
        "end_date": "20220630",
        "eps": 23.72,
        "roe": 15.6135,
        "roa": 16.5526,
        "debt_to_assets": 17.2578,
        "current_ratio": 4.948,
        "quick_ratio": 4.0993
      },
      {
        "ts_code": "600519.SH",
        "end_date": "20220331",
        "eps": 13.73,
        "roe": 8.7025,
        "roa": 9.3497,
        "debt_to_assets": 14.482,
        "current_ratio": 5.9767,
        "quick_ratio": 5.0412
      },
      {
        "ts_code": "600519.SH",
        "end_date": "20220331",
        "eps": 13.73,
        "roe": 8.7025,
        "roa": 9.3497,
        "debt_to_assets": 14.482,
        "current_ratio": 5.9767,
        "quick_ratio": 5.0412
      },
      {
        "ts_code": "600519.SH",
        "end_date": "20211231",
        "eps": 41.76,
        "roe": 29.9036,
        "roa": 31.4138,
        "debt_to_assets": 22.8127,
        "current_ratio": 3.8119,
        "quick_ratio": 3.2353
      },
      {
        "ts_code": "600519.SH",
        "end_date": "20211231",
        "eps": 41.76,
        "roe": 29.9036,
        "roa": 31.4138,
        "debt_to_assets": 22.8127,
        "current_ratio": 3.8119,
        "quick_ratio": 3.2353
      },
      {
        "ts_code": "600519.SH",
        "end_date": "20210930",
        "eps": 29.67,
        "roe": 22.204,
        "roa": 23.8532,
        "debt_to_assets": 19.5313,
        "current_ratio": 4.4324,
        "quick_ratio": 3.7329
      },
      {
        "ts_code": "600519.SH",
        "end_date": "20210930",
        "eps": 29.67,
        "roe": 22.204,
        "roa": 23.8532,
        "debt_to_assets": 19.5313,
        "current_ratio": 4.4324,
        "quick_ratio": 3.7329
      },
      {
        "ts_code": "600519.SH",
        "end_date": "20210630",
        "eps": 19.63,
        "roe": 15.2628,
        "roa": 16.2732,
        "debt_to_assets": 21.2828,
        "current_ratio": 4.0522,
        "quick_ratio": 3.3691
      },
      {
        "ts_code": "600519.SH",
        "end_date": "20210630",
        "eps": 19.63,
        "roe": 15.2628,
        "roa": 16.2732,
        "debt_to_assets": 21.2828,
        "current_ratio": 4.0522,
        "quick_ratio": 3.3691
      },
      {
        "ts_code": "600519.SH",
        "end_date": "20210331",
        "eps": 11.11,
        "roe": 8.2915,
        "roa": 9.1265,
        "debt_to_assets": 15.2071,
        "current_ratio": 5.7487,
        "quick_ratio": 4.8327
      },
      {
        "ts_code": "600519.SH",
        "end_date": "20210331",
        "eps": 11.11,
        "roe": 8.2915,
        "roa": 9.1265,
        "debt_to_assets": 15.2071,
        "current_ratio": 5.7487,
        "quick_ratio": 4.8327
      },
      {
        "ts_code": "600519.SH",
        "end_date": "20201231",
        "eps": 37.17,
        "roe": 31.4108,
        "roa": 33.2552,
        "debt_to_assets": 21.4039,
        "current_ratio": 4.0648,
        "quick_ratio": 3.4327
      },
      {
        "ts_code": "600519.SH",
        "end_date": "20201231",
        "eps": 37.17,
        "roe": 31.4108,
        "roa": 33.2552,
        "debt_to_assets": 21.4039,
        "current_ratio": 4.0648,
        "quick_ratio": 3.4327
      },
      {
        "ts_code": "600519.SH",
        "end_date": "20200930",
        "eps": 26.93,
        "roe": 23.7832,
        "roa": 25.9633,
        "debt_to_assets": 16.474,
        "current_ratio": 5.1796,
        "quick_ratio": 4.2922
      },
      {
        "ts_code": "600519.SH",
        "end_date": "20200930",
        "eps": 26.93,
        "roe": 23.7832,
        "roa": 25.9633,
        "debt_to_assets": 16.474,
        "current_ratio": 5.1796,
        "quick_ratio": 4.2922
      },
      {
        "ts_code": "600519.SH",
        "end_date": "20200630",
        "eps": 17.99,
        "roe": 16.5436,
        "roa": 17.9597,
        "debt_to_assets": 17.236,
        "current_ratio": 4.8922,
        "quick_ratio": 4.004
      },
      {
        "ts_code": "600519.SH",
        "end_date": "20200630",
        "eps": 17.99,
        "roe": 16.5436,
        "roa": 17.9597,
        "debt_to_assets": 17.236,
        "current_ratio": 4.8922,
        "quick_ratio": 4.004
      },
      {
        "ts_code": "600519.SH",
        "end_date": "20200331",
        "eps": 10.42,
        "roe": 9.1849,
        "roa": 10.1333,
        "debt_to_assets": 14.2546,
        "current_ratio": 6.1169,
        "quick_ratio": 5.138
      },
      {
        "ts_code": "600519.SH",
        "end_date": "20200331",
        "eps": 10.42,
        "roe": 9.1849,
        "roa": 10.1333,
        "debt_to_assets": 14.2546,
        "current_ratio": 6.1169,
        "quick_ratio": 5.138
      },
      {
        "ts_code": "600519.SH",
        "end_date": "20191231",
        "eps": 32.8,
        "roe": 33.1177,
        "roa": 34.2746,
        "debt_to_assets": 22.4899,
        "current_ratio": 3.8698,
        "quick_ratio": 3.2545
      },
      {
        "ts_code": "600519.SH",
        "end_date": "20191231",
        "eps": 32.8,
        "roe": 33.1177,
        "roa": 34.2746,
        "debt_to_assets": 22.4899,
        "current_ratio": 3.8698,
        "quick_ratio": 3.2545
      },
      {
        "ts_code": "600519.SH",
        "end_date": "20190930",
        "eps": 24.24,
        "roe": 25.5819,
        "roa": 26.8026,
        "debt_to_assets": 19.5191,
        "current_ratio": 4.4177,
        "quick_ratio": 3.6678
      },
      {
        "ts_code": "600519.SH",
        "end_date": "20190930",
        "eps": 24.24,
        "roe": 25.5819,
        "roa": 26.8026,
        "debt_to_assets": 19.5191,
        "current_ratio": 4.4177,
        "quick_ratio": 3.6678
      },
      {
        "ts_code": "600519.SH",
        "end_date": "20190630",
        "eps": 15.88,
        "roe": 17.5322,
        "roa": 17.4065,
        "debt_to_assets": 27.5644,
        "current_ratio": 3.1372,
        "quick_ratio": 2.6087
      },
      {
        "ts_code": "600519.SH",
        "end_date": "20190630",
        "eps": 15.88,
        "roe": 17.5322,
        "roa": 17.4065,
        "debt_to_assets": 27.5644,
        "current_ratio": 3.1372,
        "quick_ratio": 2.6087
      },
      {
        "ts_code": "600519.SH",
        "end_date": "20190331",
        "eps": 8.93,
        "roe": 9.4737,
        "roa": 9.9385,
        "debt_to_assets": 19.1172,
        "current_ratio": 4.5107,
        "quick_ratio": 3.7247
      },
      {
        "ts_code": "600519.SH",
        "end_date": "20190331",
        "eps": 8.93,
        "roe": 9.4737,
        "roa": 9.9385,
        "debt_to_assets": 19.1172,
        "current_ratio": 4.5107,
        "quick_ratio": 3.7247
      },
      {
        "ts_code": "600519.SH",
        "end_date": "20181231",
        "eps": 28.02,
        "roe": 34.4643,
        "roa": 34.5132,
        "debt_to_assets": 26.5493,
        "current_ratio": 3.2485,
        "quick_ratio": 2.6946
      },
      {
        "ts_code": "600519.SH",
        "end_date": "20181231",
        "eps": 28.02,
        "roe": 34.4643,
        "roa": 34.5132,
        "debt_to_assets": 26.5493,
        "current_ratio": 3.2485,
        "quick_ratio": 2.6946
      },
      {
        "ts_code": "600519.SH",
        "end_date": "20180930",
        "eps": 19.69,
        "roe": 25.522,
        "roa": 25.2507,
        "debt_to_assets": 27.8568,
        "current_ratio": 3.0465,
        "quick_ratio": 2.513
      },
      {
        "ts_code": "600519.SH",
        "end_date": "20180930",
        "eps": 19.69,
        "roe": 25.522,
        "roa": 25.2507,
        "debt_to_assets": 27.8568,
        "current_ratio": 3.0465,
        "quick_ratio": 2.513
      },
      {
        "ts_code": "600519.SH",
        "end_date": "20180630",
        "eps": 12.55,
        "roe": 17.0563,
        "roa": 17.173,
        "debt_to_assets": 25.7171,
        "current_ratio": 3.2262,
        "quick_ratio": 2.5648
      },
      {
        "ts_code": "600519.SH",
        "end_date": "20180630",
        "eps": 12.55,
        "roe": 17.0563,
        "roa": 17.173,
        "debt_to_assets": 25.7171,
        "current_ratio": 3.2262,
        "quick_ratio": 2.5648
      },
      {
        "ts_code": "600519.SH",
        "end_date": "20180331",
        "eps": 6.77,
        "roe": 8.8887,
        "roa": 9.0471,
        "debt_to_assets": 21.7665,
        "current_ratio": 3.8229,
        "quick_ratio": 3.0696
      },
      {
        "ts_code": "600519.SH",
        "end_date": "20180331",
        "eps": 6.77,
        "roe": 8.8887,
        "roa": 9.0471,
        "debt_to_assets": 21.7665,
        "current_ratio": 3.8229,
        "quick_ratio": 3.0696
      },
      {
        "ts_code": "600519.SH",
        "end_date": "20171231",
        "eps": 21.56,
        "roe": 32.9542,
        "roa": 31.2511,
        "debt_to_assets": 28.6683,
        "current_ratio": 2.9099,
        "quick_ratio": 2.3381
      },
      {
        "ts_code": "600519.SH",
        "end_date": "20171231",
        "eps": 21.56,
        "roe": 32.9542,
        "roa": 31.2511,
        "debt_to_assets": 28.6683,
        "current_ratio": 2.9099,
        "quick_ratio": 2.3381
      },
      {
        "ts_code": "600519.SH",
        "end_date": "20170930",
        "eps": 15.91,
        "roe": 25.4166,
        "roa": 23.6409,
        "debt_to_assets": 30.8336,
        "current_ratio": 2.6611,
        "quick_ratio": 2.1311
      },
      {
        "ts_code": "600519.SH",
        "end_date": "20170930",
        "eps": 15.91,
        "roe": 25.4166,
        "roa": 23.6409,
        "debt_to_assets": 30.8336,
        "current_ratio": 2.6611,
        "quick_ratio": 2.1311
      },
      {
        "ts_code": "600519.SH",
        "end_date": "20170630",
        "eps": 8.96,
        "roe": 15.151,
        "roa": 13.7529,
        "debt_to_assets": 34.3234,
        "current_ratio": 2.3581,
        "quick_ratio": 1.8533
      },
      {
        "ts_code": "600519.SH",
        "end_date": "20170630",
        "eps": 8.96,
        "roe": 15.151,
        "roa": 13.7529,
        "debt_to_assets": 34.3234,
        "current_ratio": 2.3581,
        "quick_ratio": 1.8533
      },
      {
        "ts_code": "600519.SH",
        "end_date": "20170331",
        "eps": 4.87,
        "roe": 8.0614,
        "roa": 7.5248,
        "debt_to_assets": 30.6986,
        "current_ratio": 2.6264,
        "quick_ratio": 2.0578
      },
      {
        "ts_code": "600519.SH",
        "end_date": "20170331",
        "eps": 4.87,
        "roe": 8.0614,
        "roa": 7.5248,
        "debt_to_assets": 30.6986,
        "current_ratio": 2.6264,
        "quick_ratio": 2.0578
      },
      {
        "ts_code": "600519.SH",
        "end_date": "20161231",
        "eps": 13.31,
        "roe": 24.4385,
        "roa": 24.0157,
        "debt_to_assets": 32.7942,
        "current_ratio": 2.436,
        "quick_ratio": 1.8789
      },
      {
        "ts_code": "600519.SH",
        "end_date": "20161231",
        "eps": 13.31,
        "roe": 24.4385,
        "roa": 24.0157,
        "debt_to_assets": 32.7942,
        "current_ratio": 2.436,
        "quick_ratio": 1.8789
      },
      {
        "ts_code": "600519.SH",
        "end_date": "20160930",
        "eps": 9.92,
        "roe": 18.8062,
        "roa": 18.8424,
        "debt_to_assets": 32.2052,
        "current_ratio": 2.4671,
        "quick_ratio": 1.9121
      },
      {
        "ts_code": "600519.SH",
        "end_date": "20160930",
        "eps": 9.92,
        "roe": 18.8062,
        "roa": 18.8424,
        "debt_to_assets": 32.2052,
        "current_ratio": 2.4671,
        "quick_ratio": 1.9121
      },
      {
        "ts_code": "600519.SH",
        "end_date": "20160630",
        "eps": 7.01,
        "roe": 13.6576,
        "roa": 14.0255,
        "debt_to_assets": 29.5075,
        "current_ratio": 2.6245,
        "quick_ratio": 1.9699
      },
      {
        "ts_code": "600519.SH",
        "end_date": "20160630",
        "eps": 7.01,
        "roe": 13.6576,
        "roa": 14.0255,
        "debt_to_assets": 29.5075,
        "current_ratio": 2.6245,
        "quick_ratio": 1.9699
      },
      {
        "ts_code": "600519.SH",
        "end_date": "20160331",
        "eps": 3.89,
        "roe": 7.3664,
        "roa": 8.1402,
        "debt_to_assets": 21.7765,
        "current_ratio": 3.5023,
        "quick_ratio": 2.5629
      },
      {
        "ts_code": "600519.SH",
        "end_date": "20160331",
        "eps": 3.89,
        "roe": 7.3664,
        "roa": 8.1402,
        "debt_to_assets": 21.7765,
        "current_ratio": 3.5023,
        "quick_ratio": 2.5629
      },
      {
        "ts_code": "600519.SH",
        "end_date": "20151231",
        "eps": 12.34,
        "roe": 26.4205,
        "roa": 28.8258,
        "debt_to_assets": 23.2526,
        "current_ratio": 3.2418,
        "quick_ratio": 2.3435
      },
      {
        "ts_code": "600519.SH",
        "end_date": "20151231",
        "eps": 12.34,
        "roe": 26.4205,
        "roa": 28.8258,
        "debt_to_assets": 23.2526,
        "current_ratio": 3.2418,
        "quick_ratio": 2.3435
      },
      {
        "ts_code": "600519.SH",
        "end_date": "20150930",
        "eps": 9.09,
        "roe": 20.1709,
        "roa": 22.4637,
        "debt_to_assets": 20.1655,
        "current_ratio": 3.6676,
        "quick_ratio": 2.6191
      },
      {
        "ts_code": "600519.SH",
        "end_date": "20150930",
        "eps": 9.09,
        "roe": 20.1709,
        "roa": 22.4637,
        "debt_to_assets": 20.1655,
        "current_ratio": 3.6676,
        "quick_ratio": 2.6191
      },
      {
        "ts_code": "600519.SH",
        "end_date": "20150630",
        "eps": 6.91,
        "roe": 13.7504,
        "roa": 16.1058,
        "debt_to_assets": 11.9937,
        "current_ratio": 6.1491,
        "quick_ratio": 4.2683
      },
      {
        "ts_code": "600519.SH",
        "end_date": "20150630",
        "eps": 6.91,
        "roe": 13.7504,
        "roa": 16.1058,
        "debt_to_assets": 11.9937,
        "current_ratio": 6.1491,
        "quick_ratio": 4.2683
      },
      {
        "ts_code": "600519.SH",
        "end_date": "20150331",
        "eps": 3.82,
        "roe": 7.8494,
        "roa": 9.203,
        "debt_to_assets": 12.853,
        "current_ratio": 5.7196,
        "quick_ratio": 3.949
      },
      {
        "ts_code": "600519.SH",
        "end_date": "20150331",
        "eps": 3.82,
        "roe": 7.8494,
        "roa": 9.203,
        "debt_to_assets": 12.853,
        "current_ratio": 5.7196,
        "quick_ratio": 3.949
      },
      {
        "ts_code": "600519.SH",
        "end_date": "20141231",
        "eps": 13.44,
        "roe": 31.9612,
        "roa": 35.8672,
        "debt_to_assets": 16.0333,
        "current_ratio": 4.5117,
        "quick_ratio": 3.0908
      },
      {
        "ts_code": "600519.SH",
        "end_date": "20141231",
        "eps": 13.44,
        "roe": 31.9612,
        "roa": 35.8672,
        "debt_to_assets": 16.0333,
        "current_ratio": 4.5117,
        "quick_ratio": 3.0908
      },
      {
        "ts_code": "600519.SH",
        "end_date": "20140930",
        "eps": 9.36,
        "roe": 23.4085,
        "roa": 26.4376,
        "debt_to_assets": 14.1688,
        "current_ratio": 5.0637,
        "quick_ratio": 3.4412
      },
      {
        "ts_code": "600519.SH",
        "end_date": "20140930",
        "eps": 9.36,
        "roe": 23.4085,
        "roa": 26.4376,
        "debt_to_assets": 14.1688,
        "current_ratio": 5.0637,
        "quick_ratio": 3.4412
      },
      {
        "ts_code": "600519.SH",
        "end_date": "20140630",
        "eps": 6.33,
        "roe": 16.4503,
        "roa": 18.377,
        "debt_to_assets": 15.5636,
        "current_ratio": 4.5053,
        "quick_ratio": 2.9614
      },
      {
        "ts_code": "600519.SH",
        "end_date": "20140630",
        "eps": 6.33,
        "roe": 16.4503,
        "roa": 18.377,
        "debt_to_assets": 15.5636,
        "current_ratio": 4.5053,
        "quick_ratio": 2.9614
      },
      {
        "ts_code": "600519.SH",
        "end_date": "20140331",
        "eps": 3.56,
        "roe": 8.3217,
        "roa": 9.487,
        "debt_to_assets": 15.3063,
        "current_ratio": 4.7259,
        "quick_ratio": 3.2423
      },
      {
        "ts_code": "600519.SH",
        "end_date": "20140331",
        "eps": 3.56,
        "roe": 8.3217,
        "roa": 9.487,
        "debt_to_assets": 15.3063,
        "current_ratio": 4.7259,
        "quick_ratio": 3.2423
      },
      {
        "ts_code": "600519.SH",
        "end_date": "20131231",
        "eps": 14.58,
        "roe": 39.4328,
        "roa": 41.8165,
        "debt_to_assets": 20.4224,
        "current_ratio": 3.7084,
        "quick_ratio": 2.6615
      },
      {
        "ts_code": "600519.SH",
        "end_date": "20131231",
        "eps": 14.58,
        "roe": 39.4328,
        "roa": 41.8165,
        "debt_to_assets": 20.4224,
        "current_ratio": 3.7084,
        "quick_ratio": 2.6615
      },
      {
        "ts_code": "600519.SH",
        "end_date": "20130930",
        "eps": 10.66,
        "roe": 30.4543,
        "roa": 32.509,
        "debt_to_assets": 19.1866,
        "current_ratio": 4.2221,
        "quick_ratio": 3.0896
      },
      {
        "ts_code": "600519.SH",
        "end_date": "20130930",
        "eps": 10.66,
        "roe": 30.4543,
        "roa": 32.509,
        "debt_to_assets": 19.1866,
        "current_ratio": 4.2221,
        "quick_ratio": 3.0896
      },
      {
        "ts_code": "600519.SH",
        "end_date": "20130630",
        "eps": 6.98,
        "roe": 21.0442,
        "roa": 22.3113,
        "debt_to_assets": 17.9768,
        "current_ratio": 4.433,
        "quick_ratio": 3.1115
      },
      {
        "ts_code": "600519.SH",
        "end_date": "20130630",
        "eps": 6.98,
        "roe": 21.0442,
        "roa": 22.3113,
        "debt_to_assets": 17.9768,
        "current_ratio": 4.433,
        "quick_ratio": 3.1115
      },
      {
        "ts_code": "600519.SH",
        "end_date": "20130331",
        "eps": 3.46,
        "roe": 9.9958,
        "roa": 11.0085,
        "debt_to_assets": 15.9177,
        "current_ratio": 5.0565,
        "quick_ratio": 3.6729
      },
      {
        "ts_code": "600519.SH",
        "end_date": "20130331",
        "eps": 3.46,
        "roe": 9.9958,
        "roa": 11.0085,
        "debt_to_assets": 15.9177,
        "current_ratio": 5.0565,
        "quick_ratio": 3.6729
      },
      {
        "ts_code": "600519.SH",
        "end_date": "20121231",
        "eps": 12.82,
        "roe": 45.0047,
        "roa": 45.755,
        "debt_to_assets": 21.2101,
        "current_ratio": 3.8026,
        "quick_ratio": 2.788
      },
      {
        "ts_code": "600519.SH",
        "end_date": "20121231",
        "eps": 12.82,
        "roe": 45.0047,
        "roa": 45.755,
        "debt_to_assets": 21.2101,
        "current_ratio": 3.8026,
        "quick_ratio": 2.788
      },
      {
        "ts_code": "600519.SH",
        "end_date": "20120930",
        "eps": 10.04,
        "roe": 37.0487,
        "roa": 38.754,
        "debt_to_assets": 17.6216,
        "current_ratio": 4.613,
        "quick_ratio": 3.4574
      },
      {
        "ts_code": "600519.SH",
        "end_date": "20120930",
        "eps": 10.04,
        "roe": 37.0487,
        "roa": 38.754,
        "debt_to_assets": 17.6216,
        "current_ratio": 4.613,
        "quick_ratio": 3.4574
      },
      {
        "ts_code": "600519.SH",
        "end_date": "20120630",
        "eps": 6.74,
        "roe": 26.4847,
        "roa": 25.7663,
        "debt_to_assets": 28.4721,
        "current_ratio": 2.8722,
        "quick_ratio": 2.1836
      },
      {
        "ts_code": "600519.SH",
        "end_date": "20120630",
        "eps": 6.74,
        "roe": 26.4847,
        "roa": 25.7663,
        "debt_to_assets": 28.4721,
        "current_ratio": 2.8722,
        "quick_ratio": 2.1836
      }
    ],
    "realtime_quote": {
      "ts_code": "600519.SH",
      "trade_date": "20251028",
      "open": 1442.0,
      "high": 1451.2,
      "low": 1441.1,
      "close": 1445.0,
      "pre_close": 1440.41,
      "change": 4.59,
      "pct_chg": 0.3187,
      "vol": 27124.33,
      "amount": 3923817.14
    },
    "news": []
  },
  "analysis": {
    "analysts": {
      "technical": {
        "trend": "震荡下行趋势，股价从1484.91高点回落至1445.0，整体呈现高位回调态势",
        "volume_analysis": "成交量呈现萎缩态势，从10月16日的45730手逐步下降至27124手，显示市场参与度降低，资金观望情绪浓厚",
        "support_resistance": "支撑位：1435.99（近期低点），阻力位：1468.8-1478.88区间（近期多次测试未能突破）",
        "short_term_outlook": "偏谨慎，股价在1440-1460区间震荡整理，需关注1435支撑位有效性，若跌破可能进一步下探",
        "medium_term_outlook": "中性偏弱，高位回调压力仍在，但基本面支撑较强，预计在1400-1500区间震荡整理",
        "technical_score": 6,
        "summary": "贵州茅台近期技术面呈现高位回调特征，成交量萎缩显示资金谨慎，短期在1440-1460区间震荡。虽然股价从高点回落，但基本面支撑依然稳固，技术面评分6分，建议关注1435支撑位和1470阻力位的突破情况"
      },
      "fundamental": {
        "profitability": "贵州茅台盈利能力极其强劲。2025年上半年实现营收910.94亿元，净利润469.87亿元，净利润率高达51.6%。从历史数据看，公司营收和净利润持续稳定增长，EPS从2012年的12.82元增长至2024年的68.64元，复合增长率显著。2025年上半年EPS已达36.18元，预计全年业绩将继续保持良好增长态势。",
        "financial_health": "财务健康度极佳。资产负债率仅为14.75%，远低于行业平均水平，表明公司负债水平极低。流动比率5.73和速动比率4.45均处于优秀水平，短期偿债能力非常强。公司总资产2922.58亿元，负债仅431.22亿元，净资产质量很高。",
        "profitability_quality": "盈利质量卓越。ROE为19.25%，ROA为21.07%，均处于行业领先水平。毛利率极高，从营业利润627.69亿元占营收893.89亿元计算，毛利率约70%，体现了公司强大的品牌溢价和成本控制能力。资产周转效率良好，盈利质量稳定可靠。",
        "cash_flow": "现金流状况良好。经营活动现金流净额131.19亿元，与净利润匹配度高。投资活动现金流净流出3.14亿元，显示公司投资相对谨慎。筹资活动现金流净流出398.93亿元，主要反映分红和回购等股东回报活动。整体现金流充裕，财务风险极低。",
        "valuation": "基于当前EPS 36.18元（半年）和历史上约30-40倍PE的估值水平，公司估值相对合理。考虑到公司稳定的增长前景、强大的品牌护城河和优秀的现金流产生能力，当前估值水平具有较好的安全边际。作为白酒行业龙头，享有合理的估值溢价。",
        "fundamental_score": 9.5,
        "summary": "贵州茅台基本面极其优秀，是A股市场的标杆企业。公司拥有强大的品牌护城河、卓越的盈利能力、极佳的财务健康状况和稳定的现金流。各项财务指标均处于行业领先水平，长期增长前景明确。唯一的扣分项在于估值相对较高，但考虑到公司的稀缺性和稳定性，整体基本面评分9.5分，属于顶级投资标的。"
      },
      "news": {
        "sentiment": "中性",
        "key_events": "无重大新闻事件",
        "impact_analysis": "无明显影响",
        "news_score": 5,
        "summary": "近期无重大新闻，市场情绪中性"
      }
    },
    "debate": {
      "bull_initial": {
        "bull_points": [
          "白酒行业龙头地位稳固，品牌护城河深厚",
          "茅台酒稀缺属性突出，供需关系长期紧张",
          "高端消费升级趋势持续，目标客群消费能力强",
          "渠道改革持续推进，直销比例提升改善盈利能力",
          "产品结构优化，非标产品占比提升带动均价上行",
          "现金流充裕，财务状况健康，分红稳定",
          "国际化战略稳步推进，海外市场增长潜力巨大",
          "酱香型白酒独特工艺形成技术壁垒",
          "库存价值稳定，具备抗通胀属性"
        ],
        "upside_potential": "基于茅台强大的品牌溢价和持续的产品提价能力，结合消费升级大趋势，预计未来3-5年有望实现年均15-20%的营收增长，净利润增速有望维持在20%以上。考虑到估值修复和业绩增长双击，股价具备30-50%的上涨空间",
        "catalysts": [
          "春节、中秋等传统旺季销售超预期",
          "新一轮产品提价落地",
          "直销渠道占比进一步提升",
          "i茅台数字营销平台用户增长",
          "海外市场拓展取得突破",
          "国企改革深化提升经营效率",
          "宏观经济复苏带动高端消费回暖"
        ],
        "buy_thesis": "贵州茅台作为中国白酒第一品牌，具备不可复制的品牌价值和稀缺属性。在消费升级和高端化趋势下，茅台的核心竞争力将进一步强化。公司通过渠道改革和产品结构优化，盈利能力持续提升。当前估值处于历史相对合理水平，是长期配置的优质标的",
        "price_target": "基于DCF估值和相对估值法，结合公司成长性和行业地位，给予12个月目标价2000-2200元，对应2024年市盈率30-35倍，较当前价位有20-30%上行空间",
        "bull_confidence": 9,
        "summary": "贵州茅台是A股市场稀缺的核心资产，品牌护城河深厚，商业模式优秀。在消费升级和高端化趋势下，公司有望持续受益。虽然短期面临宏观经济波动风险，但长期投资价值突出，是值得长期持有的优质标的"
      },
      "bear_initial": {
        "bear_points": [
          "白酒行业整体面临消费降级压力，高端白酒需求可能放缓",
          "估值水平长期处于历史高位，存在均值回归风险",
          "过度依赖高端产品线，产品结构单一化风险",
          "政策风险：反腐倡廉政策持续影响高端白酒消费场景",
          "年轻消费群体对白酒偏好下降，长期增长前景存疑",
          "库存压力可能被低估，渠道库存积压风险",
          "宏观经济下行压力影响商务宴请和礼品消费"
        ],
        "downside_risk": "当前股价已充分反映乐观预期，任何负面消息都可能引发大幅回调。考虑到白酒行业周期性特征和消费趋势变化，股价存在30-50%的下行风险。技术面缺乏明确支撑位，一旦跌破关键心理价位可能引发连锁抛售",
        "negative_catalysts": [
          "季度业绩不及预期",
          "行业政策进一步收紧",
          "宏观经济数据恶化",
          "竞争对手价格战",
          "机构投资者大规模减持",
          "消费数据持续疲软",
          "反腐政策加码"
        ],
        "sell_thesis": "在当前估值水平下，贵州茅台的风险收益比不具吸引力。考虑到行业周期性下行、消费结构变化和政策不确定性，建议投资者减持或观望。即使公司基本面依然稳健，但过高的估值已经透支了未来多年的增长预期",
        "valuation_concern": "市盈率长期维持在30倍以上，远高于国际同类消费品公司。考虑到中国经济增长放缓和人口结构变化，当前估值水平难以持续。市销率、市净率等指标均处于历史高位，存在明显的估值泡沫",
        "bear_confidence": 7,
        "summary": "贵州茅台作为白酒龙头虽然基本面相对稳健，但面临估值过高、行业周期下行、政策风险和消费趋势变化等多重压力。在当前价位建议谨慎，等待更好的买入时机或考虑减持"
      },
      "debate_rounds": [
        {
          "round": 1,
          "speaker": "bear",
          "content": "感谢对方提出的看涨观点，但我认为其中存在几个关键性的认知偏差和过度乐观的假设。让我从几个维度来阐述我的不同看法：\n\n首先，对方过分夸大了茅台的\"稀缺属性\"。虽然茅台生产工艺确实复杂，但近年来公司产能持续扩张，2023年设计产能已超过5.6万吨，实际产能还在提升。所谓的\"供需紧张\"更多是渠道控货营造的市场假象，而非真实的供需失衡。从终端动销数据看，飞天茅台的实际开瓶率并不理想，大量产品沉淀在渠道和投机客手中。\n\n其次，关于消费升级的持续性，对方忽视了结构性变化。根据中国酒业协会数据，2023年白酒行业产量同比下降，高端白酒消费增速明显放缓。更值得关注的是，Z世代消费者对白酒的接受度持续下降，尼尔森调研显示30岁以下消费者选择白酒的比例从2019年的45%降至2023年的32%。这种代际偏好的结构性变化是茅台必须面对的长期挑战。\n\n在估值方面，对方提到的30-35倍市盈率\"合理\"存在严重误判。对比全球高端消费品公司，路易威登市盈率约25倍，爱马仕约40倍，但这两家公司的全球营收占比均超过60%，而茅台海外收入占比不足5%。考虑到中国经济增长放缓的大背景，给予茅台如此高的估值溢价缺乏足够支撑。\n\n关于渠道改革，虽然直销比例确实在提升，但这也带来了新的问题。i茅台平台的推广大幅增加了营销费用，2023年三季度销售费用同比上升23%，侵蚀了利润增长。同时，传统经销商体系的调整引发了渠道矛盾，部分核心经销商开始转向其他品牌。\n\n政策风险被对方严重低估。近期中央持续强调\"过紧日子\"，限制高端消费的政策导向明确。财政部数据显示，2023年政府机关酒类采购支出同比下降35%，这对商务宴请场景产生了明显的溢出效应。\n\n最后，对方提到的国际化潜力与现实存在较大差距。茅台海外营收占比长期在3-5%徘徊，文化差异和饮用习惯使得白酒国际化进展缓慢。相比之下，苏格兰威士忌、法国干邑在中国市场的渗透率却在持续提升。\n\n综合来看，茅台当前面临的是估值泡沫、消费断层、政策压制三重压力。即使公司基本面依然稳健，但当前价位已经过度透支了未来增长预期。在宏观经济不确定性加大的背景下，建议投资者保持谨慎，等待更合理的估值水平再考虑配置。"
        },
        {
          "round": 2,
          "speaker": "bull",
          "content": "感谢对方提出的观点，但其中存在多处对事实的误读和对行业趋势的过度悲观假设。作为看涨方，我将从多个维度进行反驳，并补充论证以强化我方观点。\n\n首先，对方声称茅台的“稀缺属性”是渠道控货营造的假象，这忽视了茅台生产工艺的根本限制。茅台酒的生产严格遵循“12987”传统工艺，从投料到出厂至少需要五年时间，且受限于赤水河流域的独特生态环境，产能扩张具有天然瓶颈。2023年公司基酒产量虽达5.6万吨，但可用于成品酒的比例有限，且长期供需缺口已被第三方数据证实——例如，飞天茅台在主流电商平台的申购中签率长期低于3%，终端零售价较出厂价溢价率持续超过50%。这种刚性稀缺性是茅台品牌护城河的核心，而非短期渠道行为所能操纵。\n\n其次，对方过度放大消费降级和年轻群体偏好变化的风险，却忽略了高端消费的结构性升级趋势。尽管白酒行业总量萎缩，但高端白酒市场份额持续提升。中国酒业协会数据显示，2023年高端白酒（单价800元以上）在行业营收中占比已突破40%，较五年前翻倍。茅台的客群画像显示，其核心消费者集中于35-55岁高净值人群，该群体受经济波动影响较小，且资产性收入占比提升支撑其消费韧性。至于年轻消费群体，茅台正通过冰淇淋、咖啡等跨界联名触达新客群，i茅台平台30岁以下用户占比已超25%，证明品牌年轻化战略初见成效。\n\n关于估值问题，对方以国际奢侈品公司为参照系并不恰当。茅台具备独特的金融属性和社交货币功能，这是路易威登等消费品不具备的。其净资产收益率（ROE）常年维持在30%以上，远超国际同业，且自由现金流充沛，股息支付率稳定在50%左右。当前30-35倍市盈率对应2024年20%以上的净利润增速，PEG比率仅为1.5，仍低于许多高成长消费科技公司。历史数据显示，茅台在消费复苏周期中估值中枢通常上移至35-40倍，当前水平并未过度透支。\n\n对方对渠道改革的质疑也缺乏动态视角。直销占比提升虽短期增加营销费用，但长期将优化利润结构——2023年三季度直销渠道毛利率达96.5%，较传统经销高出逾10个百分点。i茅台平台注册用户已突破5000万，数字化营销不仅降低渠道成本，更积累了大量用户行为数据，为精准定价和产品创新提供支撑。经销商体系调整是主动优化，而非被动收缩，核心经销商流失率实际低于行业平均水平。\n\n政策风险方面，对方夸大了反腐影响的持续性。十八大以来高端白酒已历经多轮政策调整，茅台通过开发茅台1935等次高端产品、拓展个人及企业团购市场，有效对冲了政务消费下降。2023年茅台在商务宴请和礼品场景营收占比已降至30%以下，消费基础更加多元化。近期中央强调扩大内需和消费升级，反而为高端品牌提供政策暖风。\n\n最后，国际化进展虽缓但潜力巨大。茅台已建立覆盖64个国家的渠道网络，海外营收增速连续三年超20%。随着“一带一路”文化交流深化和中华文化全球影响力提升，酱香型白酒的独特口感正逐步获得海外消费者认可。参照日本威士忌的全球化路径，茅台的国际化是长期战略，短期占比低不构成核心风险。\n\n综上所述，茅台面临的短期波动不改其长期价值。在消费升级、渠道优化和产品创新的驱动下，公司有望持续实现量价齐升。结合DCF模型测算，2200元目标价对应2024年35倍PE仍属合理，建议投资者把握当前配置良机。"
        },
        {
          "round": 2,
          "speaker": "bear",
          "content": "感谢对方的进一步阐述，但我必须指出，对方的论点仍然建立在过度理想化的假设之上，忽视了现实中的结构性风险和周期性压力。我将从以下几个关键维度进行反驳和补充：\n\n首先，对方将茅台的稀缺性归因于生产工艺限制，这忽略了产能扩张的现实。根据公司公告，茅台“十四五”技改项目完成后，基酒产能将突破7万吨，稀缺性叙事正在被逐步稀释。更重要的是，终端市场数据显示，飞天茅台的实际开瓶率已从2019年的约70%下降至2023年的不足50%，大量产品沉淀在渠道和收藏领域，形成隐性库存压力。这种“伪稀缺”一旦遭遇需求端冲击，可能引发渠道抛售的连锁反应。\n\n关于消费升级趋势，对方选择性忽视了正在发生的消费分层现象。虽然高端白酒市场份额提升，但主要受益于疫情后的补偿性消费，而非可持续的结构性升级。贝恩咨询数据显示，2023年中国奢侈品消费增速已从2021年的36%放缓至12%，高净值人群消费信心指数连续三个季度下滑。茅台的核心客群——中小企业主和高级管理人员——正是本轮经济结构调整中受冲击最大的群体，其消费能力的持续性值得怀疑。\n\n在估值方面，对方用PEG比率辩护存在严重误导。茅台当前30倍市盈率对应的是营收增速已降至15%左右（2023年Q3营收同比增14.6%），净利润增速放缓至19%，PEG实际已接近1.8，显著高于消费板块平均水平。更值得警惕的是，茅台自由现金流增速已连续六个季度低于净利润增速，显示盈利质量出现隐忧。对比全球消费品巨头，宝洁、雀巢等公司在类似成长阶段的市盈率很少超过25倍。\n\n对方对渠道改革的乐观评估也忽视了执行风险。直销占比提升虽然理论上能改善毛利率，但实际操作中面临两大挑战：一是传统经销商反弹导致的渠道冲突，2023年已有多个区域出现经销商集体转投竞品的案例；二是数字化投入的边际效益递减，i茅台平台获客成本已从初期的80元/人攀升至150元/人，且用户活跃度持续下滑。\n\n政策风险方面，对方低估了新一轮反腐的深度和广度。2023年中央纪委国家监委连续发文强调“持续深化整治酒驾醉驾及背后‘四风’问题”，多地出台公务接待“禁酒令”升级版。更重要的是，房地产、金融等传统高薪行业降薪潮已明显影响高端酒类消费，这并非短期波动而是结构性转变。\n\n最后，关于国际化，对方提到的20%增速是基于极低基数，实际海外营收绝对值仍不足30亿元，且主要集中于华人圈层。参照日本威士忌的全球化路径，其成功建立在数十年文化输出和口味教育基础上，茅台短期内难以复制这一模式。\n\n综合来看，茅台面临的是估值重构、需求降级和渠道转型的三重挑战。当前股价已反映最乐观预期，任何业绩不及预期或宏观负面冲击都可能引发戴维斯双杀。从风险收益比角度，建议投资者等待更合理的估值水平，或在消费板块中寻找更具性价比的替代标的。"
        }
      ],
      "debate_summary": {
        "bull_key_points": "品牌护城河深厚，生产工艺独特形成稀缺性；高端消费升级趋势持续，核心客群消费能力强；渠道改革提升盈利能力，直销毛利率显著改善；产品结构优化带动均价上行；现金流充裕，财务状况健康；国际化战略稳步推进。",
        "bear_key_points": "估值水平长期处于历史高位，存在均值回归风险；白酒行业面临消费降级压力，高端需求可能放缓；政策风险持续影响消费场景；年轻消费群体偏好下降，长期增长存疑；渠道库存积压风险被低估；产能扩张稀释稀缺性叙事。",
        "most_convincing": "看涨方：茅台独特的生产工艺和品牌护城河确实难以复制，ROE常年维持在30%以上，自由现金流充沛，商业模式优秀。看跌方：当前30倍以上市盈率对应营收增速放缓至15%左右，PEG已达1.8，估值已充分反映乐观预期，风险收益比不具吸引力。",
        "key_disagreements": "1.稀缺性认知：看涨认为生产工艺限制形成真实稀缺，看跌认为产能扩张和低开瓶率显示'伪稀缺'；2.消费趋势判断：看涨强调结构性升级，看跌指出消费分层和降级压力；3.估值合理性：看涨认为当前估值对应成长性仍合理，看跌认为存在明显估值泡沫；4.渠道改革效果：看涨看好长期利润改善，看跌担忧执行风险和渠道冲突。",
        "balanced_view": "贵州茅台作为白酒龙头具备强大的品牌护城河和优秀的商业模式，基本面相对稳健。但当前面临估值偏高、消费趋势变化、政策不确定性等多重挑战。短期看，股价已反映较多乐观预期，上行空间受估值制约；中长期看，公司通过产品结构优化和渠道改革仍能维持稳健增长，但增速可能放缓。投资者需平衡品牌价值与估值风险的矛盾。",
        "recommendation_lean": "中性",
        "confidence_level": 7
      }
    }
  },
  "decision": {
    "action": "持有",
    "position_size": "半仓",
    "target_price": "1500-1600元",
    "stop_loss": "1350元",
    "holding_period": "中长期",
    "confidence": 7,
    "reasoning": "综合分析各方观点，贵州茅台的基本面依然极其优秀，品牌护城河深厚，盈利能力强劲，财务健康度极佳，ROE常年维持在30%以上，自由现金流充沛。然而，当前股价1445元对应30倍以上市盈率，估值已处于历史相对高位，且技术面呈现震荡下行趋势，成交量萎缩显示资金观望情绪浓厚。看跌方提出的估值泡沫、消费降级压力、政策风险等担忧具有一定合理性。在当前价位，风险收益比不够理想，但完全卖出可能错失长期价值。建议采取持有策略，等待更好的加仓时机或估值回调。",
    "key_factors": [
      "强大的品牌护城河和稀缺属性",
      "优秀的盈利能力和财务健康状况",
      "估值处于历史相对高位",
      "消费升级与降级并存的结构性变化",
      "渠道改革带来的长期利润改善潜力",
      "政策环境对高端消费的影响"
    ],
    "risks": [
      "估值过高引发的均值回归风险",
      "宏观经济下行影响高端消费需求",
      "年轻消费群体偏好变化带来的长期挑战",
      "政策收紧对商务宴请场景的持续影响",
      "渠道库存积压可能引发的抛售压力",
      "国际化进展缓慢制约增长空间"
    ],
    "summary": "贵州茅台是A股市场稀缺的优质核心资产，长期投资价值突出。但当前估值水平已充分反映乐观预期，短期上行空间有限。建议现有持仓者继续持有，享受公司稳健的基本面支撑和分红回报；新进投资者可等待更好的估值水平或明确的催化剂出现后再考虑建仓。"
  },
  "risk_assessment": {
    "market_risk": "中等。贵州茅台作为白酒龙头，受宏观经济周期影响较大。当前经济下行压力可能影响高端消费需求，市场整体波动会传导至股价。但茅台作为防御性较强的消费股，在市场下跌时相对抗跌。",
    "stock_specific_risk": "低。公司基本面极其优秀，品牌护城河深厚，盈利能力强劲（ROE常年30%以上），财务健康度极佳（资产负债率仅14.75%），现金流充沛。主要风险在于估值偏高和消费趋势变化。",
    "industry_risk": "中等偏高。白酒行业面临消费降级压力、政策风险（反腐倡廉影响商务消费）、年轻消费群体偏好变化等挑战。但高端白酒市场份额持续提升，结构性升级趋势仍在。",
    "liquidity_risk": "低。作为A股龙头股，贵州茅台成交活跃，流动性充足。近期成交量虽有萎缩，但仍保持较高水平，不会出现流动性枯竭风险。",
    "valuation_risk": "高。当前30倍以上市盈率处于历史相对高位，PEG达1.8，估值已充分反映乐观预期。相比国际同类消费品公司估值偏高，存在均值回归风险。",
    "sentiment_risk": "中等。近期无重大负面新闻，但市场对高端消费前景存在分歧。政策环境和宏观经济变化可能引发情绪波动。",
    "overall_risk_level": "中",
    "risk_score": 6,
    "risk_control_suggestions": [
      "严格控制仓位，建议不超过总资产的15%",
      "设置1350元止损位，严格执行风险控制",
      "分批建仓，避免在单一价位重仓",
      "密切关注季度财报和消费数据变化",
      "定期评估估值水平，防范估值回归风险",
      "关注政策动向和行业监管变化"
    ],
    "max_position_size": "不超过总资产的15%",
    "monitoring_points": [
      "季度营收和净利润增速是否低于15%",
      "直销渠道占比提升进度和毛利率变化",
      "终端动销数据和渠道库存水平",
      "宏观经济数据和消费信心指数",
      "政策环境变化对高端消费的影响",
      "年轻消费群体接受度变化趋势",
      "估值水平变化，PE是否回落至25倍以下"
    ],
    "summary": "贵州茅台基本面优秀，品牌护城河深厚，是A股稀缺的核心资产。但当前估值偏高（30倍PE），已充分反映乐观预期，风险收益比不够理想。主要风险包括估值回归、消费降级压力、政策风险和行业周期性调整。建议现有持仓者继续持有，享受稳健基本面和分红回报；新进投资者等待更好的估值水平或明确的催化剂出现。总体风险等级中等，风险评分6分。"
  },
  "analysis_time": "2025-10-28T15:43:29.148269",
  "duration_seconds": 207.675488
}